fab_cohort/__init__.py
fab_cohort/cohort.py
fabcohort-0.3.1.dist-info/METADATA
fabcohort-0.3.1.dist-info/WHEEL
fabcohort-0.3.1.dist-info/top_level.txt
fabcohort-0.3.1.dist-info/RECORD
