Metadata-Version: 2.1
Name: fabcohort
Version: 0.3.1
Summary: for cohort analysis
Home-page: https://github.com/linliD/fabcohort/
Author: Linli Ding
Author-email: linli@joinbonnet.com
License: MIT
Platform: UNKNOWN
Classifier: Intended Audience :: Developers
Classifier: License :: OSI Approved :: MIT License
Classifier: Programming Language :: Python
Classifier: Programming Language :: Python :: 3
Classifier: Programming Language :: Python :: 3.6
Classifier: Programming Language :: Python :: 3.7
Classifier: Programming Language :: Python :: 3.8
Classifier: Programming Language :: Python :: 3.9
Classifier: Operating System :: OS Independent
Requires-Dist: pandas
Requires-Dist: numpy
